ibats_huobi_trader/__init__.py
ibats_huobi_trader/config.py
ibats_huobi_trader/agent/__init__.py
ibats_huobi_trader/agent/md_agent.py
ibats_huobi_trader/agent/td_agent.py
ibats_huobi_trader/analysis/__init__.py
ibats_huobi_trader/analysis/account.py
ibats_huobi_trader/backend/__init__.py
ibats_huobi_trader/backend/check.py
IBATS_Huobi_Trader-0.1.8.dist-info/LICENSE
IBATS_Huobi_Trader-0.1.8.dist-info/METADATA
IBATS_Huobi_Trader-0.1.8.dist-info/WHEEL
IBATS_Huobi_Trader-0.1.8.dist-info/top_level.txt
IBATS_Huobi_Trader-0.1.8.dist-info/RECORD
