Metadata-Version: 2.1
Name: IBATS-Huobi-Trader
Version: 0.1.8
Summary: 作为IBATS架构的 Trader 端，用于连接Huobi 火币交易所进行相应的交易及账户信息获取等动作
Home-page: https://github.com/IBATS/IBATS_HuobiTrader
Author: MG
Author-email: mmmaaaggg@163.com
License: UNKNOWN
Platform: UNKNOWN
Classifier: Programming Language :: Python :: 3 :: Only
Classifier: Programming Language :: Python :: 3.6
Classifier: Programming Language :: Python :: 3.7
Classifier: Operating System :: Microsoft :: Windows
Classifier: Operating System :: Unix
Classifier: Operating System :: POSIX
Classifier: License :: OSI Approved :: MIT License
Classifier: Development Status :: 5 - Production/Stable
Classifier: Environment :: No Input/Output (Daemon)
Classifier: Intended Audience :: Developers
Classifier: Natural Language :: Chinese (Simplified)
Classifier: Topic :: Software Development
Requires-Python: >=3.6
Requires-Dist: IBATS-Huobi-Feeder
Requires-Dist: mysqlclient (>=1.3.8)
Requires-Dist: numpy (==1.14.4)
Requires-Dist: pandas (==0.23.0)
Requires-Dist: SQLAlchemy (==1.2.8)
Requires-Dist: click (>=7.0)
